mango_distributions/__init__.py
mango_distributions-0.0.1.dist-info/METADATA
mango_distributions-0.0.1.dist-info/WHEEL
mango_distributions-0.0.1.dist-info/top_level.txt
mango_distributions-0.0.1.dist-info/RECORD
