Metadata-Version: 2.1
Name: mango-distributions
Version: 0.0.1
Summary: Mango Distributions
Home-page: UNKNOWN
Author: JackR
Author-email: jackrasa@example.com
License: UNKNOWN
Platform: UNKNOWN
Classifier: Programming Language :: Python :: 3
Requires-Python: >=3.6
